[[{"__type__":"cc.Prefab","_name":"jackpot-effect-prefab","data":{"__id__":1}},{"__type__":"cc.Node","_name":"jackpot-effect-prefab","_children":[{"__id__":2}],"_components":[{"__type__":"e8a1233kdpJUp/ZHOXRluJV","node":{"__id__":1},"jackpotSkeleton":{"__id__":4},"balanceLabel":{"__id__":3}},{"__id__":4}],"_prefab":{"__type__":"cc.PrefabInfo","root":{"__id__":1},"asset":{"__uuid__":"4b+MIu4jlI6JNCNdYzAMZd"},"fileId":"49ffcCNtMFPeaEPJTTSkj9r"}},{"__type__":"cc.Node","_name":"balance-label","_parent":{"__id__":1},"_components":[{"__id__":3}],"_prefab":{"__type__":"cc.PrefabInfo","root":{"__id__":1},"asset":{"__uuid__":"4b+MIu4jlI6JNCNdYzAMZd"},"fileId":"25e8e6OUo5Jh7NwNyQfG9Y/"},"_contentSize":{"__type__":"cc.Size","width":181.33,"height":68.75},"_position":{"__type__":"cc.Vec3","y":-65}},{"__type__":"cc.Label","node":{"__id__":2},"_useOriginalSize":false,"_string":"10.000","_N$string":"10.000","_fontSize":55,"_lineHeight":80,"_N$file":{"__uuid__":"beS1IkWNVBOL50JhAzQp+C"},"_isSystemFontUsed":false,"_N$horizontalAlign":1,"_N$verticalAlign":1},{"__type__":"sp.Skeleton","node":{"__id__":1},"_N$skeletonData":{"__uuid__":"77K4C/XiZD7rLGzn8UEvkl"}}],{"__type__":"sp.SkeletonData","_name":"jackpot","skeletonJsonStr":"{\"skeleton\":{\"hash\":\"t3aB9xuNEYDarAQVfOP4cyn15O4\",\"spine\":\"3.6.53\",\"width\":505.47,\"height\":349.2,\"images\":\"./img/\"},\"bones\":[{\"name\":\"root\"},{\"name\":\"glow\",\"parent\":\"root\",\"length\":91.37,\"rotation\":89.69,\"x\":-0.3,\"y\":13.56,\"scaleX\":0.6,\"scaleY\":0.6},{\"name\":\"glow2\",\"parent\":\"root\",\"length\":43.12,\"rotation\":89.67,\"x\":194.1,\"y\":13.84,\"scaleX\":1.4,\"scaleY\":1.4},{\"name\":\"glow3\",\"parent\":\"root\",\"length\":43.12,\"rotation\":89.67,\"x\":-204.89,\"y\":26.8,\"scaleX\":1.4,\"scaleY\":1.4},{\"name\":\"glow4\",\"parent\":\"root\",\"length\":91.37,\"rotation\":89.69,\"x\":-0.3,\"y\":13.56,\"scaleX\":0.6,\"scaleY\":0.6},{\"name\":\"text_effect\",\"parent\":\"root\",\"length\":31.12,\"rotation\":90,\"y\":-24.35},{\"name\":\"text_still\",\"parent\":\"root\",\"length\":31.12,\"rotation\":90,\"y\":-24.35}],\"slots\":[{\"name\":\"glow\",\"bone\":\"glow\",\"attachment\":\"Layer 222\"},{\"name\":\"glow4\",\"bone\":\"glow4\",\"attachment\":\"Layer 222\",\"blend\":\"screen\"},{\"name\":\"text_still\",\"bone\":\"text_still\",\"attachment\":\"nohu\"},{\"name\":\"text_effect\",\"bone\":\"text_effect\",\"attachment\":\"nohu\"},{\"name\":\"glow2\",\"bone\":\"glow2\",\"attachment\":\"glow2\",\"blend\":\"additive\"},{\"name\":\"glow3\",\"bone\":\"glow3\",\"attachment\":\"glow2\",\"blend\":\"additive\"}],\"skins\":{\"default\":{\"glow\":{\"Layer 222\":{\"x\":-0.01,\"y\":-0.3,\"rotation\":-89.69,\"width\":583,\"height\":582}},\"glow2\":{\"glow2\":{\"x\":-1.26,\"y\":-2.21,\"rotation\":-89.67,\"width\":63,\"height\":64}},\"glow3\":{\"glow2\":{\"x\":-1.26,\"y\":-2.21,\"rotation\":-89.67,\"width\":63,\"height\":64}},\"glow4\":{\"Layer 222\":{\"x\":-0.01,\"y\":-0.3,\"rotation\":-89.69,\"width\":583,\"height\":582}},\"text_effect\":{\"nohu\":{\"x\":68.65,\"y\":-9.07,\"rotation\":-90,\"width\":501,\"height\":219}},\"text_still\":{\"nohu\":{\"x\":68.65,\"y\":-9.07,\"rotation\":-90,\"width\":501,\"height\":219}}}},\"animations\":{\"nohu\":{\"slots\":{\"glow\":{\"color\":[{\"time\":0,\"color\":\"ffffff00\"},{\"time\":0.1667,\"color\":\"ffffffff\",\"curve\":\"stepped\"},{\"time\":4.6667,\"color\":\"ffffffff\"},{\"time\":5.3333,\"color\":\"ffffff00\"}],\"attachment\":[{\"time\":0,\"name\":\"Layer 222\"},{\"time\":5.3333,\"name\":\"Layer 222\"}]},\"glow2\":{\"color\":[{\"time\":0,\"color\":\"ffffff00\",\"curve\":\"stepped\"},{\"time\":0.1667,\"color\":\"ffffff00\"},{\"time\":0.6667,\"color\":\"ffffffff\"},{\"time\":1.3333,\"color\":\"ffffff00\",\"curve\":\"stepped\"},{\"time\":2.6667,\"color\":\"ffffff00\"},{\"time\":3.1667,\"color\":\"ffffffff\"},{\"time\":3.8333,\"color\":\"ffffff00\",\"curve\":\"stepped\"},{\"time\":5.3333,\"color\":\"ffffff00\"}],\"attachment\":[{\"time\":0,\"name\":\"glow2\"},{\"time\":5.3333,\"name\":\"glow2\"}]},\"glow3\":{\"color\":[{\"time\":0,\"color\":\"ffffff00\",\"curve\":\"stepped\"},{\"time\":0.3333,\"color\":\"ffffff00\"},{\"time\":0.8667,\"color\":\"ffffffff\"},{\"time\":1.3333,\"color\":\"ffffff00\",\"curve\":\"stepped\"},{\"time\":2.8333,\"color\":\"ffffff00\"},{\"time\":3.3667,\"color\":\"ffffffff\"},{\"time\":3.8333,\"color\":\"ffffff00\",\"curve\":\"stepped\"},{\"time\":5.3333,\"color\":\"ffffff00\"}],\"attachment\":[{\"time\":0,\"name\":\"glow2\"},{\"time\":5.3333,\"name\":\"glow2\"}]},\"glow4\":{\"color\":[{\"time\":0,\"color\":\"ffffff00\"},{\"time\":0.1667,\"color\":\"ffffffff\"},{\"time\":0.4333,\"color\":\"ffffff00\",\"curve\":\"stepped\"},{\"time\":5.3333,\"color\":\"ffffff00\"}],\"attachment\":[{\"time\":0,\"name\":\"Layer 222\"},{\"time\":5.3333,\"name\":\"Layer 222\"}]},\"text_effect\":{\"color\":[{\"time\":0,\"color\":\"ffffff00\",\"curve\":\"stepped\"},{\"time\":0.1333,\"color\":\"ffffff00\"},{\"time\":0.1667,\"color\":\"ffffffff\"},{\"time\":0.5,\"color\":\"ffffff00\"}],\"attachment\":[{\"time\":0,\"name\":\"nohu\"},{\"time\":5.3333,\"name\":\"nohu\"}]},\"text_still\":{\"color\":[{\"time\":0,\"color\":\"ffffff00\"},{\"time\":0.1667,\"color\":\"ffffffff\",\"curve\":\"stepped\"},{\"time\":5.3333,\"color\":\"ffffffff\"}],\"attachment\":[{\"time\":0,\"name\":\"nohu\"},{\"time\":5.3333,\"name\":\"nohu\"}]}},\"bones\":{\"text_still\":{\"scale\":[{\"time\":0,\"x\":0.191,\"y\":0.191},{\"time\":0.1667,\"x\":1.1,\"y\":1.1},{\"time\":0.2667,\"x\":1,\"y\":1,\"curve\":\"stepped\"},{\"time\":5.3333,\"x\":1,\"y\":1}]},\"glow\":{\"rotate\":[{\"time\":0,\"angle\":0},{\"time\":2.6667,\"angle\":-172.57},{\"time\":5.3333,\"angle\":13.38}],\"scale\":[{\"time\":0,\"x\":0.323,\"y\":0.323},{\"time\":0.1667,\"x\":1.1,\"y\":1.1},{\"time\":0.2667,\"x\":1,\"y\":1,\"curve\":\"stepped\"},{\"time\":5.3333,\"x\":1,\"y\":1}]},\"glow3\":{\"rotate\":[{\"time\":0,\"angle\":0,\"curve\":\"stepped\"},{\"time\":0.3333,\"angle\":0},{\"time\":0.8667,\"angle\":-166.13},{\"time\":1.3333,\"angle\":26.49},{\"time\":2.8333,\"angle\":0},{\"time\":3.3667,\"angle\":-166.13},{\"time\":3.8333,\"angle\":26.49,\"curve\":\"stepped\"},{\"time\":5.3333,\"angle\":26.49}]},\"glow2\":{\"rotate\":[{\"time\":0,\"angle\":0,\"curve\":\"stepped\"},{\"time\":0.1667,\"angle\":0},{\"time\":0.6667,\"angle\":-166.14},{\"time\":1.3333,\"angle\":22},{\"time\":2.6667,\"angle\":0},{\"time\":3.1667,\"angle\":-166.14},{\"time\":3.8333,\"angle\":22,\"curve\":\"stepped\"},{\"time\":5.3333,\"angle\":22}]},\"glow4\":{\"scale\":[{\"time\":0,\"x\":0.226,\"y\":0.226},{\"time\":0.1667,\"x\":1.5,\"y\":1.5},{\"time\":0.4333,\"x\":1.8,\"y\":1.8,\"curve\":\"stepped\"},{\"time\":5.3333,\"x\":1.8,\"y\":1.8}]},\"text_effect\":{\"scale\":[{\"time\":0,\"x\":1,\"y\":1,\"curve\":\"stepped\"},{\"time\":0.1667,\"x\":1,\"y\":1},{\"time\":0.5,\"x\":1.234,\"y\":1.234}]}},\"drawOrder\":[{\"time\":0},{\"time\":5.3333}]}}}","_skeletonJson":{"skeleton":{"hash":"t3aB9xuNEYDarAQVfOP4cyn15O4","spine":"3.6.53","width":505.47,"height":349.2,"images":"./img/"},"bones":[{"name":"root"},{"name":"glow","parent":"root","length":91.37,"rotation":89.69,"x":-0.3,"y":13.56,"scaleX":0.6,"scaleY":0.6},{"name":"glow2","parent":"root","length":43.12,"rotation":89.67,"x":194.1,"y":13.84,"scaleX":1.4,"scaleY":1.4},{"name":"glow3","parent":"root","length":43.12,"rotation":89.67,"x":-204.89,"y":26.8,"scaleX":1.4,"scaleY":1.4},{"name":"glow4","parent":"root","length":91.37,"rotation":89.69,"x":-0.3,"y":13.56,"scaleX":0.6,"scaleY":0.6},{"name":"text_effect","parent":"root","length":31.12,"rotation":90,"y":-24.35},{"name":"text_still","parent":"root","length":31.12,"rotation":90,"y":-24.35}],"slots":[{"name":"glow","bone":"glow","attachment":"Layer 222"},{"name":"glow4","bone":"glow4","attachment":"Layer 222","blend":"screen"},{"name":"text_still","bone":"text_still","attachment":"nohu"},{"name":"text_effect","bone":"text_effect","attachment":"nohu"},{"name":"glow2","bone":"glow2","attachment":"glow2","blend":"additive"},{"name":"glow3","bone":"glow3","attachment":"glow2","blend":"additive"}],"skins":{"default":{"glow":{"Layer 222":{"x":-0.01,"y":-0.3,"rotation":-89.69,"width":583,"height":582}},"glow2":{"glow2":{"x":-1.26,"y":-2.21,"rotation":-89.67,"width":63,"height":64}},"glow3":{"glow2":{"x":-1.26,"y":-2.21,"rotation":-89.67,"width":63,"height":64}},"glow4":{"Layer 222":{"x":-0.01,"y":-0.3,"rotation":-89.69,"width":583,"height":582}},"text_effect":{"nohu":{"x":68.65,"y":-9.07,"rotation":-90,"width":501,"height":219}},"text_still":{"nohu":{"x":68.65,"y":-9.07,"rotation":-90,"width":501,"height":219}}}},"animations":{"nohu":{"slots":{"glow":{"color":[{"time":0,"color":"ffffff00"},{"time":0.1667,"color":"ffffffff","curve":"stepped"},{"time":4.6667,"color":"ffffffff"},{"time":5.3333,"color":"ffffff00"}],"attachment":[{"time":0,"name":"Layer 222"},{"time":5.3333,"name":"Layer 222"}]},"glow2":{"color":[{"time":0,"color":"ffffff00","curve":"stepped"},{"time":0.1667,"color":"ffffff00"},{"time":0.6667,"color":"ffffffff"},{"time":1.3333,"color":"ffffff00","curve":"stepped"},{"time":2.6667,"color":"ffffff00"},{"time":3.1667,"color":"ffffffff"},{"time":3.8333,"color":"ffffff00","curve":"stepped"},{"time":5.3333,"color":"ffffff00"}],"attachment":[{"time":0,"name":"glow2"},{"time":5.3333,"name":"glow2"}]},"glow3":{"color":[{"time":0,"color":"ffffff00","curve":"stepped"},{"time":0.3333,"color":"ffffff00"},{"time":0.8667,"color":"ffffffff"},{"time":1.3333,"color":"ffffff00","curve":"stepped"},{"time":2.8333,"color":"ffffff00"},{"time":3.3667,"color":"ffffffff"},{"time":3.8333,"color":"ffffff00","curve":"stepped"},{"time":5.3333,"color":"ffffff00"}],"attachment":[{"time":0,"name":"glow2"},{"time":5.3333,"name":"glow2"}]},"glow4":{"color":[{"time":0,"color":"ffffff00"},{"time":0.1667,"color":"ffffffff"},{"time":0.4333,"color":"ffffff00","curve":"stepped"},{"time":5.3333,"color":"ffffff00"}],"attachment":[{"time":0,"name":"Layer 222"},{"time":5.3333,"name":"Layer 222"}]},"text_effect":{"color":[{"time":0,"color":"ffffff00","curve":"stepped"},{"time":0.1333,"color":"ffffff00"},{"time":0.1667,"color":"ffffffff"},{"time":0.5,"color":"ffffff00"}],"attachment":[{"time":0,"name":"nohu"},{"time":5.3333,"name":"nohu"}]},"text_still":{"color":[{"time":0,"color":"ffffff00"},{"time":0.1667,"color":"ffffffff","curve":"stepped"},{"time":5.3333,"color":"ffffffff"}],"attachment":[{"time":0,"name":"nohu"},{"time":5.3333,"name":"nohu"}]}},"bones":{"text_still":{"scale":[{"time":0,"x":0.191,"y":0.191},{"time":0.1667,"x":1.1,"y":1.1},{"time":0.2667,"x":1,"y":1,"curve":"stepped"},{"time":5.3333,"x":1,"y":1}]},"glow":{"rotate":[{"time":0,"angle":0},{"time":2.6667,"angle":-172.57},{"time":5.3333,"angle":13.38}],"scale":[{"time":0,"x":0.323,"y":0.323},{"time":0.1667,"x":1.1,"y":1.1},{"time":0.2667,"x":1,"y":1,"curve":"stepped"},{"time":5.3333,"x":1,"y":1}]},"glow3":{"rotate":[{"time":0,"angle":0,"curve":"stepped"},{"time":0.3333,"angle":0},{"time":0.8667,"angle":-166.13},{"time":1.3333,"angle":26.49},{"time":2.8333,"angle":0},{"time":3.3667,"angle":-166.13},{"time":3.8333,"angle":26.49,"curve":"stepped"},{"time":5.3333,"angle":26.49}]},"glow2":{"rotate":[{"time":0,"angle":0,"curve":"stepped"},{"time":0.1667,"angle":0},{"time":0.6667,"angle":-166.14},{"time":1.3333,"angle":22},{"time":2.6667,"angle":0},{"time":3.1667,"angle":-166.14},{"time":3.8333,"angle":22,"curve":"stepped"},{"time":5.3333,"angle":22}]},"glow4":{"scale":[{"time":0,"x":0.226,"y":0.226},{"time":0.1667,"x":1.5,"y":1.5},{"time":0.4333,"x":1.8,"y":1.8,"curve":"stepped"},{"time":5.3333,"x":1.8,"y":1.8}]},"text_effect":{"scale":[{"time":0,"x":1,"y":1,"curve":"stepped"},{"time":0.1667,"x":1,"y":1},{"time":0.5,"x":1.234,"y":1.234}]}},"drawOrder":[{"time":0},{"time":5.3333}]}}},"_atlasText":"\njackpot.png\nsize: 1024,1024\nformat: RGBA8888\nfilter: Linear,Linear\nrepeat: none\nLayer 222\n  rotate: false\n  xy: 2, 223\n  size: 583, 582\n  orig: 583, 582\n  offset: 0, 0\n  index: -1\nglow2\n  rotate: false\n  xy: 587, 741\n  size: 63, 64\n  orig: 63, 64\n  offset: 0, 0\n  index: -1\nnohu\n  rotate: false\n  xy: 2, 2\n  size: 501, 219\n  orig: 501, 219\n  offset: 0, 0\n  index: -1\n","textures":[{"__uuid__":"1absdEbd1N3IABQ3aIilvS"}],"textureNames":["jackpot.png"]}]